<DataObject comparison="Ordinal">
  <Section id="">
    <Subsections>
      <Section id="General">
        <Subsections />
        <Entries>
          <Entry key="ElapsedTime">
            <double>3.7679198</double>
          </Entry>
          <Entry key="StartedAt">
            <dateTime>2019-01-06T23:38:23.6184602+05:30</dateTime>
          </Entry>
          <Entry key="EndedAt">
            <dateTime>2019-01-06T23:38:27.38638+05:30</dateTime>
          </Entry>
          <Entry key="ReplayStatus">
            <LastReplayRunStatus>Passed</LastReplayRunStatus>
          </Entry>
          <Entry key="NumberOfReplayErrors">
            <int>0</int>
          </Entry>
          <Entry key="NumberOfReplayCriticalErrors">
            <int>0</int>
          </Entry>
          <Entry key="NumberOfCompilationErrors">
            <int>0</int>
          </Entry>
        </Entries>
      </Section>
    </Subsections>
    <Entries>
      <Entry key="Iterations">
        <int>4</int>
      </Entry>
    </Entries>
  </Section>
</DataObject>